flexgen/__init__.py
flexgen/compression.py
flexgen/dist_flex_opt.py
flexgen/dist_utils.py
flexgen/flex_opt.py
flexgen/opt_config.py
flexgen/profile_bandwidth.py
flexgen/profile_matmul.py
flexgen/pytorch_backend.py
flexgen/timer.py
flexgen/utils.py
flexgen-1.0.dist-info/LICENSE
flexgen-1.0.dist-info/METADATA
flexgen-1.0.dist-info/WHEEL
flexgen-1.0.dist-info/top_level.txt
flexgen-1.0.dist-info/RECORD
