Metadata-Version: 2.1
Name: flexgen
Version: 1.0
Summary: Running large language models like OPT-175B/GPT-3 on a single GPU. Focusing on high-throughput large-batch generation.
Project-URL: Homepage, https://github.com/FMInference/FlexGen
Project-URL: Bug Tracker, https://github.com/FMInference/FlexGen/issues
Classifier: Programming Language :: Python :: 3
Classifier: License :: OSI Approved :: MIT License
Requires-Python: >=3.7
License-File: LICENSE
Requires-Dist: numpy
Requires-Dist: tqdm
Requires-Dist: pulp
Requires-Dist: attrs
Requires-Dist: transformers (>=4.24)
Requires-Dist: torch (>=1.12)
